{"legislative_session": "2026", "identifier": "HB7415", "title": "AN ACT RELATING TO EDUCATION -- ESTABLISHMENT OF CHARTER PUBLIC SCHOOLS", "from_organization": "~{\"classification\": \"lower\"}", "classification": ["bill"], "subject": [], "abstracts": [{"note": "summary", "abstract": "This act would bar the council from granting approval to create or expand a charter school beginning operations in 26-27 school year and bars the state from approving or appropriating funds to a new charter school not approved before July 1, 2025."}], "other_titles": [], "other_identifiers": [], "actions": [{"description": "01/30/2026 Introduced, referred to House Education", "date": "2026-01-30", "organization_id": "~{\"classification\": \"lower\"}", "classification": ["introduction", "referral-committee"], "related_entities": []}], "sponsorships": [{"name": "Messier", "classification": "primary", "entity_type": "person", "primary": true, "person_id": "~{\"name\": \"Messier\"}", "organization_id": null}, {"name": "Kislak", "classification": "primary", "entity_type": "person", "primary": true, "person_id": "~{\"name\": \"Kislak\"}", "organization_id": null}, {"name": "Casey", "classification": "primary", "entity_type": "person", "primary": true, "person_id": "~{\"name\": \"Casey\"}", "organization_id": null}, {"name": "Furtado", "classification": "primary", "entity_type": "person", "primary": true, "person_id": "~{\"name\": \"Furtado\"}", "organization_id": null}, {"name": "Kazarian", "classification": "primary", "entity_type": "person", "primary": true, "person_id": "~{\"name\": \"Kazarian\"}", "organization_id": null}, {"name": "Alzate", "classification": "primary", "entity_type": "person", "primary": true, "person_id": "~{\"name\": \"Alzate\"}", "organization_id": null}, {"name": "Sanchez", "classification": "primary", "entity_type": "person", "primary": true, "person_id": "~{\"name\": \"Sanchez\"}", "organization_id": null}, {"name": "Serpa", "classification": "primary", "entity_type": "person", "primary": true, "person_id": "~{\"name\": \"Serpa\"}", "organization_id": null}, {"name": "Fogarty", "classification": "primary", "entity_type": "person", "primary": true, "person_id": "~{\"name\": \"Fogarty\"}", "organization_id": null}, {"name": "Phillips", "classification": "primary", "entity_type": "person", "primary": true, "person_id": "~{\"name\": \"Phillips\"}", "organization_id": null}], "related_bills": [], "versions": [{"note": "7415", "links": [{"url": "http://webserver.rilegislature.gov/BillText/BillText26/HouseText26/H7415.pdf", "media_type": "application/pdf"}], "date": "", "classification": ""}], "documents": [], "citations": [], "sources": [{"url": "https://status.rilegislature.gov/", "note": ""}], "extras": {}, "jurisdiction": {"id": "ocd-jurisdiction/country:us/state:ri/government", "name": "Rhode Island", "classification": "state", "division_id": "ocd-division/country:us/state:ri"}, "scraped_at": "2026-01-31T08:33:19+00:00", "_id": "7efa0ef8-fe7f-11f0-9d3e-4ee56b5db980"}