{"legislative_session": "2026", "identifier": "SB2183", "title": "AN ACT RELATING TO MOTOR AND OTHER VEHICLES -- REGISTRATION OF VEHICLES", "from_organization": "~{\"classification\": \"upper\"}", "classification": ["bill"], "subject": [], "abstracts": [{"note": "summary", "abstract": "Eliminates the registration and service charge fees for National Guard plates."}], "other_titles": [], "other_identifiers": [], "actions": [{"description": "01/16/2026 Introduced, referred to Senate Special Legislation and Veterans Affairs", "date": "2026-01-16", "organization_id": "~{\"classification\": \"upper\"}", "classification": ["introduction", "referral-committee"], "related_entities": []}], "sponsorships": [{"name": "Felag", "classification": "primary", "entity_type": "person", "primary": true, "person_id": "~{\"name\": \"Felag\"}", "organization_id": null}, {"name": "Appollonio", "classification": "primary", "entity_type": "person", "primary": true, "person_id": "~{\"name\": \"Appollonio\"}", "organization_id": null}, {"name": "Lauria", "classification": "primary", "entity_type": "person", "primary": true, "person_id": "~{\"name\": \"Lauria\"}", "organization_id": null}, {"name": "Gallo", "classification": "primary", "entity_type": "person", "primary": true, "person_id": "~{\"name\": \"Gallo\"}", "organization_id": null}, {"name": "Burke", "classification": "primary", "entity_type": "person", "primary": true, "person_id": "~{\"name\": \"Burke\"}", "organization_id": null}, {"name": "LaMountain", "classification": "primary", "entity_type": "person", "primary": true, "person_id": "~{\"name\": \"LaMountain\"}", "organization_id": null}, {"name": "Britto", "classification": "primary", "entity_type": "person", "primary": true, "person_id": "~{\"name\": \"Britto\"}", "organization_id": null}], "related_bills": [], "versions": [{"note": "2183", "links": [{"url": "http://webserver.rilegislature.gov/BillText/BillText26/SenateText26/S2183.pdf", "media_type": "application/pdf"}], "date": "", "classification": ""}], "documents": [], "citations": [], "sources": [{"url": "https://status.rilegislature.gov/", "note": ""}], "extras": {}, "jurisdiction": {"id": "ocd-jurisdiction/country:us/state:ri/government", "name": "Rhode Island", "classification": "state", "division_id": "ocd-division/country:us/state:ri"}, "scraped_at": "2026-02-02T08:45:14+00:00", "_id": "7e0d3494-0013-11f1-8e3b-ba82e162a4c6"}