{"legislative_session": "2026", "identifier": "SB2059", "title": "AN ACT RELATING TO TAXATION -- TAX SALES", "from_organization": "~{\"classification\": \"upper\"}", "classification": ["bill"], "subject": [], "abstracts": [{"note": "summary", "abstract": "Requires specific notice of the tax sale to the taxpayer with a copy of this \u00a7 44-9-10 attached thereto. Failure to do so would render the tax sale null and void."}], "other_titles": [], "other_identifiers": [], "actions": [{"description": "01/09/2026 Introduced, referred to Senate Judiciary", "date": "2026-01-09", "organization_id": "~{\"classification\": \"upper\"}", "classification": ["introduction", "referral-committee"], "related_entities": []}], "sponsorships": [{"name": "Gu", "classification": "primary", "entity_type": "person", "primary": true, "person_id": "~{\"name\": \"Gu\"}", "organization_id": null}, {"name": "Murray", "classification": "primary", "entity_type": "person", "primary": true, "person_id": "~{\"name\": \"Murray\"}", "organization_id": null}, {"name": "Bissaillon", "classification": "primary", "entity_type": "person", "primary": true, "person_id": "~{\"name\": \"Bissaillon\"}", "organization_id": null}, {"name": "DiPalma", "classification": "primary", "entity_type": "person", "primary": true, "person_id": "~{\"name\": \"DiPalma\"}", "organization_id": null}, {"name": "Burke", "classification": "primary", "entity_type": "person", "primary": true, "person_id": "~{\"name\": \"Burke\"}", "organization_id": null}, {"name": "DiMario", "classification": "primary", "entity_type": "person", "primary": true, "person_id": "~{\"name\": \"DiMario\"}", "organization_id": null}, {"name": "Famiglietti", "classification": "primary", "entity_type": "person", "primary": true, "person_id": "~{\"name\": \"Famiglietti\"}", "organization_id": null}], "related_bills": [], "versions": [{"note": "2059", "links": [{"url": "http://webserver.rilegislature.gov/BillText/BillText26/SenateText26/S2059.pdf", "media_type": "application/pdf"}], "date": "", "classification": ""}], "documents": [], "citations": [], "sources": [{"url": "https://status.rilegislature.gov/", "note": ""}], "extras": {}, "jurisdiction": {"id": "ocd-jurisdiction/country:us/state:ri/government", "name": "Rhode Island", "classification": "state", "division_id": "ocd-division/country:us/state:ri"}, "scraped_at": "2026-01-10T08:28:34+00:00", "_id": "5aa9e550-edfe-11f0-8a07-c65c36928d30"}