{"legislative_session": "2026", "identifier": "HB8029", "title": "AN ACT RELATING TO TAXATION -- COLLECTION OF TAXES GENERALLY", "from_organization": "~{\"classification\": \"lower\"}", "classification": ["bill"], "subject": [], "abstracts": [{"note": "summary", "abstract": "Adds the town of Tiverton to those towns specifically named to tax any person for either a mobile or manufactured home and automatically lien the a mobile or manufactured home."}], "other_titles": [], "other_identifiers": [], "actions": [{"description": "02/27/2026 Introduced, referred to House Municipal Government & Housing", "date": "2026-02-27", "organization_id": "~{\"classification\": \"lower\"}", "classification": ["introduction", "referral-committee"], "related_entities": []}], "sponsorships": [{"name": "Edwards", "classification": "primary", "entity_type": "person", "primary": true, "person_id": "~{\"name\": \"Edwards\"}", "organization_id": null}], "related_bills": [], "versions": [{"note": "8029", "links": [{"url": "http://webserver.rilegislature.gov/BillText/BillText26/HouseText26/H8029.pdf", "media_type": "application/pdf"}], "date": "", "classification": ""}], "documents": [], "citations": [], "sources": [{"url": "https://status.rilegislature.gov/", "note": ""}], "extras": {}, "jurisdiction": {"id": "ocd-jurisdiction/country:us/state:ri/government", "name": "Rhode Island", "classification": "state", "division_id": "ocd-division/country:us/state:ri"}, "scraped_at": "2026-03-05T08:43:50+00:00", "_id": "6edf6842-186f-11f1-93fc-06e485156134"}