{"legislative_session": "2026", "identifier": "SB2037", "title": "AN ACT RELATING TO TAXATION -- PROPERTY SUBJECT TO TAXATION", "from_organization": "~{\"classification\": \"upper\"}", "classification": ["bill"], "subject": [], "abstracts": [{"note": "summary", "abstract": "Authorizes the town of Barrington to provide a tax dollar credit reduction for legally blind persons by ordinance."}], "other_titles": [], "other_identifiers": [], "actions": [{"description": "01/09/2026 Introduced, referred to Senate Housing and Municipal Government", "date": "2026-01-09", "organization_id": "~{\"classification\": \"upper\"}", "classification": ["introduction", "referral-committee"], "related_entities": []}], "sponsorships": [{"name": "Lauria", "classification": "primary", "entity_type": "person", "primary": true, "person_id": "~{\"name\": \"Lauria\"}", "organization_id": null}], "related_bills": [], "versions": [{"note": "2037", "links": [{"url": "http://webserver.rilegislature.gov/BillText/BillText26/SenateText26/S2037.pdf", "media_type": "application/pdf"}], "date": "", "classification": ""}], "documents": [], "citations": [], "sources": [{"url": "https://status.rilegislature.gov/", "note": ""}], "extras": {}, "jurisdiction": {"id": "ocd-jurisdiction/country:us/state:ri/government", "name": "Rhode Island", "classification": "state", "division_id": "ocd-division/country:us/state:ri"}, "scraped_at": "2026-01-29T08:41:38+00:00", "_id": "53a9bb64-fcee-11f0-bf87-22a5b0f24c4a"}