{"legislative_session": "2026", "identifier": "HB7957", "title": "AN ACT RELATING TO STATE AFFAIRS AND GOVERNMENT -- DIGITAL ASSET KEYS--PROHIBITION OF PRODUCTION OF PRIVATE KEYS", "from_organization": "~{\"classification\": \"lower\"}", "classification": ["bill"], "subject": [], "abstracts": [{"note": "summary", "abstract": "Prohibits the compelled production of a private key as it relates to a digital asset, digital identity or other interest or right."}], "other_titles": [], "other_identifiers": [], "actions": [{"description": "02/27/2026 Introduced, referred to House Innovation, Internet, & Technology", "date": "2026-02-27", "organization_id": "~{\"classification\": \"lower\"}", "classification": ["introduction", "referral-committee"], "related_entities": []}, {"description": "02/27/2026 Scheduled for hearing and/or consideration  (03/05/2026)", "date": "2026-02-27", "organization_id": "~{\"classification\": \"legislature\"}", "classification": [], "related_entities": []}], "sponsorships": [{"name": "Casey", "classification": "primary", "entity_type": "person", "primary": true, "person_id": "~{\"name\": \"Casey\"}", "organization_id": null}], "related_bills": [], "versions": [{"note": "7957", "links": [{"url": "http://webserver.rilegislature.gov/BillText/BillText26/HouseText26/H7957.pdf", "media_type": "application/pdf"}], "date": "", "classification": ""}], "documents": [], "citations": [], "sources": [{"url": "https://status.rilegislature.gov/", "note": ""}], "extras": {}, "jurisdiction": {"id": "ocd-jurisdiction/country:us/state:ri/government", "name": "Rhode Island", "classification": "state", "division_id": "ocd-division/country:us/state:ri"}, "scraped_at": "2026-02-28T08:31:45+00:00", "_id": "eadfd592-147f-11f1-b34c-92bd8a465227"}